pycus/__init__.py
pycus/__main__.py
pycus/_version.py
pycus/commands.py
pycus/tests/__init__.py
pycus/tests/helper.py
pycus/tests/test_commands.py
pycus-20.11.0.dist-info/LICENSE
pycus-20.11.0.dist-info/METADATA
pycus-20.11.0.dist-info/WHEEL
pycus-20.11.0.dist-info/entry_points.txt
pycus-20.11.0.dist-info/top_level.txt
pycus-20.11.0.dist-info/RECORD
